parser/__init__.py
renderers/__init__.py
renderers/swagger/__init__.py
server/__init__.py
server/http_server.py
strut-1.1.1.data/scripts/strut
strut-1.1.1.data/scripts/strut-server
tests/__init__.py
tests/utils/__init__.py
strut-1.1.1.dist-info/METADATA
strut-1.1.1.dist-info/WHEEL
strut-1.1.1.dist-info/top_level.txt
strut-1.1.1.dist-info/RECORD
