Metadata-Version: 2.1
Name: strut
Version: 1.1.1
Summary: Define HTTP APIs easily.
Home-page: https://github.com/trevorgrayson/strut
Author: trevor grayson
Author-email: trevor@ipsumllc.com
License: UNKNOWN
Platform: UNKNOWN
Classifier: Programming Language :: Python :: 2
Classifier: License :: OSI Approved :: MIT License
